cloudshell/__init__.py
cloudshell/firewall/__init__.py
cloudshell/firewall/fortinet/__init__.py
cloudshell/firewall/fortinet/autoload/__init__.py
cloudshell/firewall/fortinet/autoload/snmp_autoload.py
cloudshell/firewall/fortinet/cli/__init__.py
cloudshell/firewall/fortinet/cli/cli_handler.py
cloudshell/firewall/fortinet/cli/command_modes.py
cloudshell/firewall/fortinet/command_actions/__init__.py
cloudshell/firewall/fortinet/command_actions/base.py
cloudshell/firewall/fortinet/command_actions/snmp_actions.py
cloudshell/firewall/fortinet/command_actions/system_actions.py
cloudshell/firewall/fortinet/command_templates/__init__.py
cloudshell/firewall/fortinet/command_templates/configuration.py
cloudshell/firewall/fortinet/command_templates/snmp_templates.py
cloudshell/firewall/fortinet/flows/__init__.py
cloudshell/firewall/fortinet/flows/autoload_flow.py
cloudshell/firewall/fortinet/flows/disable_snmp_flow.py
cloudshell/firewall/fortinet/flows/enable_snmp_flow.py
cloudshell/firewall/fortinet/flows/load_firmware_flow.py
cloudshell/firewall/fortinet/flows/restore_flow.py
cloudshell/firewall/fortinet/flows/save_flow.py
cloudshell/firewall/fortinet/helpers/__init__.py
cloudshell/firewall/fortinet/helpers/cached_property.py
cloudshell/firewall/fortinet/helpers/exceptions.py
cloudshell/firewall/fortinet/mibs/FORTINET-CORE-MIB.py
cloudshell/firewall/fortinet/mibs/FORTINET-FORTIGATE-MIB.py
cloudshell/firewall/fortinet/mibs/HCNUM-TC.py
cloudshell/firewall/fortinet/mibs/IANAifType-MIB.py
cloudshell/firewall/fortinet/mibs/IF-MIB.py
cloudshell/firewall/fortinet/mibs/IPV6-TC.py
cloudshell/firewall/fortinet/mibs/SNMPv2-MIB.py
cloudshell/firewall/fortinet/mibs/__init__.py
cloudshell/firewall/fortinet/runners/__init__.py
cloudshell/firewall/fortinet/runners/autoload_runner.py
cloudshell/firewall/fortinet/runners/configuration_runner.py
cloudshell/firewall/fortinet/runners/firmware_runner.py
cloudshell/firewall/fortinet/snmp/__init__.py
cloudshell_firewall_fortinet-1.1.1.dist-info/METADATA
cloudshell_firewall_fortinet-1.1.1.dist-info/RECORD
cloudshell_firewall_fortinet-1.1.1.dist-info/WHEEL
cloudshell_firewall_fortinet-1.1.1.dist-info/top_level.txt
