Metadata-Version: 2.1
Name: cloudshell-firewall-fortinet
Version: 1.1.1
Summary: QualiSystems firewall FortiNet specific package
Home-page: http://www.qualisystems.com/
Author: QualiSystems
Author-email: info@qualisystems.com
License: UNKNOWN
Platform: UNKNOWN
Requires-Dist: cloudshell-firewall (<3.1,>=3.0)
Requires-Dist: cloudshell-networking-devices (<2.7,>=2.6)
